voiceagent/__init__.py
voiceagent/transcriber.py
voiceagent/voice_agent.py
voiceagent-0.0.3.dist-info/METADATA
voiceagent-0.0.3.dist-info/WHEEL
voiceagent-0.0.3.dist-info/RECORD
