Metadata-Version: 2.1
Name: voiceagent
Version: 0.0.3
Summary: A package to make it easy to interact with LLM's using voice
License: MIT
Author: Sami Maameri
Author-email: ssmaameri@gmail.com
Requires-Python: >=3.12,<4.0
Classifier: License :: OSI Approved :: MIT License
Classifier: Programming Language :: Python :: 3
Classifier: Programming Language :: Python :: 3.12
Requires-Dist: assemblyai (>=0.33.0,<0.34.0)
Requires-Dist: elevenlabs (>=1.7.0,<2.0.0)
Requires-Dist: openai (>=1.43.0,<2.0.0)
Requires-Dist: pyaudio (>=0.2.14,<0.3.0)
